podex/__init__.py
podex-0.0.1.dist-info/METADATA
podex-0.0.1.dist-info/WHEEL
podex-0.0.1.dist-info/entry_points.txt
podex-0.0.1.dist-info/RECORD
